README.txt
bootstrap.py
buildout.cfg
plone30.cfg
plone31.cfg
project.cfg
setup.cfg
setup.py
iw/__init__.py
iw.fss.egg-info/PKG-INFO
iw.fss.egg-info/SOURCES.txt
iw.fss.egg-info/dependency_links.txt
iw.fss.egg-info/entry_points.txt
iw.fss.egg-info/namespace_packages.txt
iw.fss.egg-info/not-zip-safe
iw.fss.egg-info/requires.txt
iw.fss.egg-info/top_level.txt
iw/fss/ABOUT
iw/fss/CHANGES
iw/fss/FileSystemStorage.py
iw/fss/LICENSE
iw/fss/README.txt
iw/fss/TESTED_WITH
iw/fss/TODO
iw/fss/__init__.py
iw/fss/atct.zcml
iw/fss/conffile.py
iw/fss/config.py
iw/fss/configure.zcml
iw/fss/customconfig.py
iw/fss/interfaces.py
iw/fss/meta.zcml
iw/fss/modifier.gif
iw/fss/modifier.py
iw/fss/modulealiases.py
iw/fss/product.txt
iw/fss/profiles.zcml
iw/fss/rdf.py
iw/fss/setuphandlers.py
iw/fss/strategy.py
iw/fss/tool.gif
iw/fss/traversable.py
iw/fss/upgrades.py
iw/fss/upgrades.zcml
iw/fss/utils.py
iw/fss/zcml.py
iw/fss/Extensions/Install_inactive.py
iw/fss/Extensions/__init__.py
iw/fss/Extensions/migrationExample.py
iw/fss/Extensions/toolbox.py
iw/fss/bin/build_fs_tree.py
iw/fss/bin/strategymigrator.py
iw/fss/browser/__init__.py
iw/fss/browser/configure.zcml
iw/fss/browser/controlpanel.py
iw/fss/browser/fss_controlpanel_master.pt
iw/fss/browser/fss_documentation_form.pt
iw/fss/browser/fss_maintenance_form.pt
iw/fss/browser/fss_management_form.pt
iw/fss/browser/fss_tool.gif
iw/fss/configuration/__init__.py
iw/fss/configuration/datatypes.py
iw/fss/configuration/schema.py
iw/fss/configuration/schema.xml
iw/fss/doc/FAQ
iw/fss/doc/METADATA_VERSIONS.txt
iw/fss/doc/SCREENSHOTS
iw/fss/doc/fss_item_view.png
iw/fss/doc/fss_maintenance_configlet.png
iw/fss/doc/fss_management_configlet.png
iw/fss/doc/icon.png
iw/fss/doctests/utility.txt
iw/fss/doctests/versioning.txt
iw/fss/etc/plone-filesystemstorage.conf.in
iw/fss/examples/FSSItem.py
iw/fss/examples/__init__.py
iw/fss/i18n/iw.fss-plone-fr.po
iw/fss/i18n/iw.fss-plone.pot
iw/fss/locales/README.txt
iw/fss/locales/iw.fss.pot
iw/fss/locales/iw.fss_manual.pot
iw/fss/locales/make_mos.sh
iw/fss/locales/rebuild_pot.sh
iw/fss/locales/sync_pos.sh
iw/fss/locales/cs/LC_MESSAGES/iw.fss.mo
iw/fss/locales/cs/LC_MESSAGES/iw.fss.po
iw/fss/locales/fr/LC_MESSAGES/iw.fss.mo
iw/fss/locales/fr/LC_MESSAGES/iw.fss.po
