Metadata-Version: 1.0
Name: iw.fss
Version: 2.7.6
Summary: Archetypes storage for storing fields raw values on the file system.
Home-page: http://svn.plone.org/svn/collective/iw.fss/
Author: Ingeniweb
Author-email: support@ingeniweb.com
License: GPL
Keywords: fss plone
Platform: UNKNOWN
Classifier: Framework :: Plone
Classifier: Programming Language :: Python
Classifier: Topic :: Software Development :: Libraries :: Python Modules
